{
    "ApprovalTime": "2017-03-26T04:44:16Z",
    "AutoApprovalTime": "2017-03-26T04:44:01Z",
    "AssignmentId": "31LVTDXBL7ABOU8W2TPDZ1ZM9C0RLX",
    "WorkerId": "A1H162QMRV01SA",
    "answers": {
        "data": {
            "ids_causaldata": [
                "strengths0causalRelations15"
            ],
            "causaldata": [
                "Level of Honesty",
                "Memories of Important Life Milestones",
                "Level of Loyalty",
                "Level of Wholesomeness",
                "Goals for Personal Life",
                "Aesthetic Preferences",
                "Important Childhood Memories",
                "Memories of Important Life Milestones",
                "Cherished Memories of Time Spent with Parents/Family",
                "Knowledge of Music",
                "Memories of Important Life Milestones",
                "Cherished Memories of Time Spent with Parents/Family",
                "Favorite Hobbies/Activities",
                "Intelligence Level",
                "Favorite Hobbies/Activities",
                "Knowledge of Math",
                "Aesthetic Preferences",
                "Important Childhood Memories",
                "Memories of Important Life Milestones",
                "Level of Honesty",
                "Level of Loyalty",
                "Goals for Personal Life",
                "Reliability",
                "Level of Honesty",
                "Level of Loyalty",
                "Level of Wholesomeness",
                "Reliability",
                "Intelligence Level",
                "Important Childhood Memories",
                "Cherished Memories of Time Spent with Parents/Family",
                "pass",
                "pass",
                "Level of Loyalty",
                "Level of Wholesomeness",
                "Goals for Personal Life",
                "none",
                "none",
                "none",
                "Important Childhood Memories",
                "Cherished Memories of Time Spent with Parents/Family",
                "Goals for Personal Life",
                "Goals for Personal Life"
            ],
            "phase_order": [
                "MapFirst",
                "ChangeFirst"
            ],
            "phase_order_temp": [],
            "causaldata_strengths": [
                "2",
                "2",
                "3",
                "3",
                "3",
                "1",
                "2",
                "3",
                "2",
                "2",
                "2",
                "3",
                "2",
                "2",
                "3",
                "2",
                "3",
                "2",
                "2",
                "2",
                "2",
                "2",
                "2",
                "1",
                "2",
                "3",
                "2",
                "1",
                "2",
                "1",
                "NA",
                "NA",
                "2",
                "2",
                "2",
                "0",
                "0",
                "0",
                "2",
                "2",
                "3",
                "2"
            ],
            "identitydata": [
                "100",
                "0",
                "0",
                "0",
                "0",
                "100",
                "0",
                "0",
                "100",
                "0",
                "100",
                "0",
                "0",
                "0",
                "0",
                "0"
            ],
            "tempcausaldata": [
                "Goals for Personal Life"
            ],
            "temptarget": [
                "Level of Loyalty"
            ],
            "order_causaltask": [],
            "causaltargets": [
                "Reliability",
                "Reliability",
                "Reliability",
                "Reliability",
                "Reliability",
                "Reliability",
                "Favorite Hobbies/Activities",
                "Favorite Hobbies/Activities",
                "Favorite Hobbies/Activities",
                "Favorite Hobbies/Activities",
                "Important Childhood Memories",
                "Important Childhood Memories",
                "Important Childhood Memories",
                "Knowledge of Music",
                "Knowledge of Music",
                "Intelligence Level",
                "Intelligence Level",
                "Cherished Memories of Time Spent with Parents/Family",
                "Cherished Memories of Time Spent with Parents/Family",
                "Level of Wholesomeness",
                "Level of Wholesomeness",
                "Level of Wholesomeness",
                "Level of Wholesomeness",
                "Goals for Personal Life",
                "Goals for Personal Life",
                "Goals for Personal Life",
                "Goals for Personal Life",
                "Knowledge of Math",
                "Degree of Shyness",
                "Degree of Shyness",
                "attention_check",
                "attention_check",
                "Level of Honesty",
                "Level of Honesty",
                "Level of Honesty",
                "Height",
                "Level of Hunger",
                "Aesthetic Preferences",
                "Memories of Important Life Milestones",
                "Memories of Important Life Milestones",
                "Memories of Important Life Milestones",
                "Level of Loyalty"
            ],
            "order_identitytask": [
                "Important Childhood Memories",
                "Level of Honesty",
                "Knowledge of Math",
                "Intelligence Level",
                "Height",
                "Memories of Important Life Milestones",
                "Level of Loyalty",
                "Level of Wholesomeness",
                "Cherished Memories of Time Spent with Parents/Family",
                "Goals for Personal Life",
                "Level of Hunger",
                "Aesthetic Preferences",
                "Favorite Hobbies/Activities",
                "Reliability",
                "Knowledge of Music",
                "Degree of Shyness"
            ],
            "demographics": [
                [
                    {
                        "name": "Age",
                        "value": "27"
                    },
                    {
                        "name": "Language",
                        "value": "English"
                    },
                    {
                        "name": "Ethnicity",
                        "value": "asian"
                    },
                    {
                        "name": "Gender",
                        "value": "female"
                    },
                    {
                        "name": "Browser",
                        "value": "Google Chrome"
                    },
                    {
                        "name": "Issues",
                        "value": "No"
                    }
                ]
            ],
            "practicedata": [
                true,
                true,
                "2",
                "3",
                true,
                true,
                "2",
                false,
                true,
                "2"
            ]
        }
    },
    "AcceptTime": "2017-03-26T04:27:08Z",
    "HITId": "3P0I4CQYVY7LFRUMOCAAPXF9HNLWO9",
    "Assignment": "",
    "AssignmentStatus": "Approved",
    "SubmitTime": "2017-03-26T04:39:01Z"
}